watertap/__init__.py
watertap/conftest.py
watertap/custom_exceptions.py
watertap/core/__init__.py
watertap/core/control_volume_isothermal.py
watertap/core/initialization_mixin.py
watertap/core/membrane_channel0d.py
watertap/core/membrane_channel1d.py
watertap/core/membrane_channel_base.py
watertap/core/solvers.py
watertap/core/wt_database.py
watertap/core/zero_order_base.py
watertap/core/zero_order_diso.py
watertap/core/zero_order_electricity.py
watertap/core/zero_order_properties.py
watertap/core/zero_order_pt.py
watertap/core/zero_order_sido.py
watertap/core/zero_order_sido_reactive.py
watertap/core/zero_order_siso.py
watertap/core/util/__init__.py
watertap/core/util/chemistry.py
watertap/core/util/initialization.py
watertap/core/util/misc.py
watertap/core/util/periodic_table.csv
watertap/core/util/scaling.py
watertap/core/util/model_diagnostics/__init__.py
watertap/core/util/model_diagnostics/infeasible.py
watertap/core/util/model_diagnostics/ipopt_initialization.py
watertap/core/util/model_diagnostics/tests/__init__.py
watertap/core/util/model_diagnostics/tests/test_infeasible.py
watertap/core/util/model_diagnostics/tests/test_ipopt_initialization.py
watertap/core/util/tests/__init__.py
watertap/core/util/tests/test_chemistry.py
watertap/core/util/tests/test_initialization.py
watertap/core/util/tests/test_misc.py
watertap/core/util/tests/test_scaling.py
watertap/costing/__init__.py
watertap/costing/multiple_choice_costing_block.py
watertap/costing/util.py
watertap/costing/watertap_costing_package.py
watertap/costing/zero_order_costing.py
watertap/costing/tests/__init__.py
watertap/costing/tests/test_costing_base.py
watertap/costing/tests/test_multiple_choice_costing_block.py
watertap/costing/tests/test_util.py
watertap/costing/tests/test_zero_order_costing.py
watertap/costing/unit_models/__init__.py
watertap/costing/unit_models/anaerobic_digester.py
watertap/costing/unit_models/clarifier.py
watertap/costing/unit_models/compressor.py
watertap-1.5.0.dist-info/licenses/LICENSE.md
watertap-1.5.0.dist-info/METADATA
watertap-1.5.0.dist-info/WHEEL
watertap-1.5.0.dist-info/entry_points.txt
watertap-1.5.0.dist-info/top_level.txt
watertap-1.5.0.dist-info/RECORD
