Metadata-Version: 2.4
Name: watertap
Version: 1.5.0
Summary: WaterTAP modeling library
Home-page: https://github.com/watertap-org/watertap
Author: NAWI team
License: BSD
Keywords: water systems,chemical engineering,process modeling,filtration,desalination,nawi
Classifier: Development Status :: 3 - Alpha
Classifier: Intended Audience :: End Users/Desktop
Classifier: Intended Audience :: Science/Research
Classifier: License :: OSI Approved :: BSD License
Classifier: Natural Language :: English
Classifier: Operating System :: MacOS
Classifier: Operating System :: Microsoft :: Windows
Classifier: Operating System :: Unix
Classifier: Programming Language :: Python
Classifier: Programming Language :: Python :: 3
Classifier: Programming Language :: Python :: 3.9
Classifier: Programming Language :: Python :: 3.10
Classifier: Programming Language :: Python :: 3.11
Classifier: Programming Language :: Python :: Implementation :: CPython
Classifier: Topic :: Scientific/Engineering :: Mathematics
Classifier: Topic :: Scientific/Engineering :: Chemistry
Classifier: Topic :: Software Development :: Libraries :: Python Modules
Classifier: Programming Language :: Python :: 3 :: Only
Requires-Python: >=3.9
License-File: LICENSE.md
Requires-Dist: idaes-pse>=2.10.0
Requires-Dist: pyomo>=6.6.1
Requires-Dist: watertap-solvers
Requires-Dist: pyyaml
Requires-Dist: parameter-sweep>=0.1.0
Requires-Dist: numpy
Requires-Dist: pint<0.25
Provides-Extra: testing
Requires-Dist: pytest; extra == "testing"
Requires-Dist: pandas; extra == "testing"
Requires-Dist: nbmake!=1.5.1; extra == "testing"
Requires-Dist: nbconvert; extra == "testing"
Requires-Dist: idaes-flowsheet-processor>=0.1.dev4; extra == "testing"
Provides-Extra: notebooks
Requires-Dist: jupyter; extra == "notebooks"
Requires-Dist: ipykernel; extra == "notebooks"
Provides-Extra: oli-api
Requires-Dist: requests; extra == "oli-api"
Requires-Dist: cryptography; extra == "oli-api"
Dynamic: author
Dynamic: classifier
Dynamic: description
Dynamic: description-content-type
Dynamic: home-page
Dynamic: keywords
Dynamic: license
Dynamic: license-file
Dynamic: provides-extra
Dynamic: requires-dist
Dynamic: requires-python
Dynamic: summary
